src/dds/dds_amp.v
// DDS Amplitude Modulator
module dds_amp(
    input  wire        clk,
    input  wire        rst_n,
    input  wire [7:0]  wave_in,
    input  wire [8:0]  a_word,
    output reg  [7:0]  wave_out
);

    wire signed [8:0]  wave_signed = {1'b0, wave_in} - 9'sd128;
    // a_word is 9-bit (0-511), full-scale = 511 ≈ divide by 512
    // mult_result[17:9] = product / 512, correct amplitude scaling
    wire signed [18:0] mult_result = wave_signed * $signed({1'b0, a_word});
    wire signed [9:0]  scaled_wave = $signed(mult_result[17:9]) + 10'sd128;

    always @(posedge clk or negedge rst_n) begin
        if(!rst_n)
            wave_out <= 8'd128;
        else if(scaled_wave < 0)
            wave_out <= 8'd0;
        else if(scaled_wave > 10'sd255)
            wave_out <= 8'd255;
        else
            wave_out <= scaled_wave[7:0];   
    end

endmodule

src/sim/sin_sim.v
// Behavioral sine ROM model for simulation
// Replaces Altera altsyncram-based sin.v — no Quartus libraries needed.
// 10-bit address, 10-bit signed sine output centered around 512.
`timescale 1ns/1ps

module sin (
    input  wire [9:0]  address,
    input  wire        clock,
    output reg  [9:0]  q
);

    reg [9:0] sine_table [0:1023];

    integer i;
    real    phase;
    real    val;

    initial begin
        for (i = 0; i < 1024; i = i + 1) begin
            phase = 2.0 * 3.141592653589793 * i / 1024.0;
            val   = 512.0 + 511.0 * $sin(phase);
            sine_table[i] = $rtoi(val);
        end
    end

    always @(posedge clock) begin
        q <= sine_table[address];
    end

endmodule

src/dds/dds_phase.v
module dds_phase(
    input  wire        clk,
    input  wire        rst_n,
    input  wire        phase_clr,
    input  wire [31:0] f_word,
    output wire [9:0]  rom_addr
);

    reg [31:0] phase_acc;

    always @(posedge clk or negedge rst_n) begin
        if(!rst_n)
            phase_acc <= 32'd0;
        else if(phase_clr)
            phase_acc <= 32'd0;
        else
            phase_acc <= phase_acc + f_word;
    end

    assign rom_addr = phase_acc[31:22];

endmodule

src/dds/dds_top.v
module dds_top(
    input                 clk,
    input                 rst_n,
    input                 phase_clr,
    input        [31:0]   f_word,
    input        [8:0]    a_word,
    output       [7:0]    wave_out
);

    wire [9:0] rom_addr;
    wire [9:0] sin_q_raw;
    wire [7:0] wave_raw;

    dds_phase u_dds_phase(
        .clk       (clk),
        .rst_n     (rst_n),
        .phase_clr (phase_clr),
        .f_word    (f_word),
        .rom_addr  (rom_addr)
    );

    sin u_sin (
        .address (rom_addr),
        .clock   (clk),
        .q       (sin_q_raw)
    );

    // The ROM stores 10-bit unsigned sine data centered at 512.
    // Keeping the upper 8 bits preserves the sinusoidal shape and 128 midpoint.
    assign wave_raw = sin_q_raw[9:2];

    dds_amp u_dds_amp(
        .clk      (clk),
        .rst_n    (rst_n),
        .wave_in  (wave_raw),
        .a_word   (a_word),
        .wave_out (wave_out)
    );

endmodule

src/dds/dds_sweep_ctrl.v
module dds_sweep_ctrl #(
    parameter integer CLK_FREQ_HZ           = 50000000,
    parameter integer START_FREQ_HZ         = 100,
    parameter integer STOP_FREQ_HZ          = 10000,
    parameter integer STEP_FREQ_HZ          = 100,
    parameter integer STEP_PERIOD_CLKS      = 50000,
    parameter integer REPEAT_SWEEP          = 1,
    parameter integer RESET_PHASE_EACH_STEP = 1
)(
    input  wire        clk,
    input  wire        rst_n,
    input  wire        sweep_en,
    input  wire        restart,
    output reg  [31:0] f_word,
    output reg         phase_clr,
    output reg         step_sync,
    output reg         sweep_busy,
    output reg         sweep_done
);

    function [31:0] hz_to_fword;
        input integer freq_hz;
        reg   [63:0] numerator;
        begin
            numerator   = freq_hz;
            numerator   = numerator << 32;
            hz_to_fword = numerator / CLK_FREQ_HZ;
        end
    endfunction

    localparam [31:0] START_WORD = hz_to_fword(START_FREQ_HZ);
    localparam [31:0] STOP_WORD  = hz_to_fword(STOP_FREQ_HZ);
    localparam [31:0] STEP_WORD  = hz_to_fword(STEP_FREQ_HZ);
    localparam        SWEEP_UP   = (STOP_WORD >= START_WORD);
    localparam integer SAFE_STEP_PERIOD_CLKS = (STEP_PERIOD_CLKS > 0) ? STEP_PERIOD_CLKS : 1;

    reg [31:0] dwell_cnt;


    always @(posedge clk or negedge rst_n) begin
        if(!rst_n) begin
            f_word     <= START_WORD;
            phase_clr  <= 1'b0;
            step_sync  <= 1'b0;
            sweep_busy <= 1'b0;
            sweep_done <= 1'b0;
            dwell_cnt  <= 32'd0;
        end else begin
            phase_clr <= 1'b0;
            step_sync <= 1'b0;
            sweep_done <= 1'b0;

            if(restart) begin
                f_word     <= START_WORD;
                dwell_cnt  <= 32'd0;
                sweep_busy <= sweep_en;
                phase_clr  <= 1'b1;
                step_sync  <= 1'b1;
            end else if(sweep_en) begin
                sweep_busy <= 1'b1;

                if(dwell_cnt >= (SAFE_STEP_PERIOD_CLKS - 1)) begin
                    dwell_cnt <= 32'd0;
                    step_sync <= 1'b1;
                    if(RESET_PHASE_EACH_STEP != 0)
                        phase_clr <= 1'b1;

                    if(STEP_WORD == 0) begin
                        sweep_done <= 1'b1;
                        if(REPEAT_SWEEP != 0) begin
                            f_word <= START_WORD;
                        end else begin
                            f_word <= START_WORD;
                            sweep_busy <= 1'b0;
                        end
                    end else begin
                        if(SWEEP_UP) begin
                            if(f_word >= STOP_WORD) begin
                                sweep_done <= 1'b1;
                                if(REPEAT_SWEEP != 0) begin
                                    f_word <= START_WORD;
                                end else begin
                                    f_word <= STOP_WORD;
                                    sweep_busy <= 1'b0;
                                end
                            end else if((f_word + STEP_WORD) >= STOP_WORD) begin
                                f_word <= STOP_WORD;
                            end else begin
                                f_word <= f_word + STEP_WORD;
                            end
                        end else begin
                            if(f_word <= STOP_WORD) begin
                                sweep_done <= 1'b1;
                                if(REPEAT_SWEEP != 0) begin
                                    f_word <= START_WORD;
                                end else begin
                                    f_word <= STOP_WORD;
                                    sweep_busy <= 1'b0;
                                end
                            end else if(f_word <= (STOP_WORD + STEP_WORD)) begin
                                f_word <= STOP_WORD;
                            end else begin
                                f_word <= f_word - STEP_WORD;
                            end
                        end
                    end
                end else begin
                    dwell_cnt <= dwell_cnt + 32'd1;
                end
            end else begin
                f_word     <= START_WORD;
                dwell_cnt  <= 32'd0;
                sweep_busy <= 1'b0;
            end
        end
    end

endmodule

src/sim/dds_sweep_tb.v
`timescale 1ns/1ps

module dds_sweep_tb;

    reg clk;
    reg rst_n;

    localparam integer DDS_A_WORD_WIDTH = 9;
    localparam integer CLK_HALF_NS      = 10;             // 50 MHz clock
    localparam integer MAX_SIM_CYCLES   = 20000;          // timeout

    // ── sweep parameters (match uut_ctrl) ────────────────────
    localparam integer CLK_FREQ_HZ      = 50000000;
    localparam integer START_FREQ_HZ    = 1000000;
    localparam integer STOP_FREQ_HZ     = 4000000;
    localparam integer STEP_FREQ_HZ     = 1000000;
    localparam integer STEP_PERIOD_CLKS = 500;            // 每段500个时钟, 1MHz下可见10个完整正弦周期

    // ── DUT wires ────────────────────────────────────────────
    wire [31:0] f_word;
    wire        phase_clr;
    wire        step_sync;
    wire        sweep_busy;
    wire        sweep_done;
    wire [7:0]  wave_out;
    wire [DDS_A_WORD_WIDTH-1:0] amp_word;

    // ── thesis display signals ───────────────────────────────
    reg  [7:0]  freq_step;          // 频率档位号 (1,2,3,4...), 波形窗口可显示

    // ── book‑keeping ─────────────────────────────────────────
    integer     cycle_count;
    integer     step_count;
    integer     csv_fd;
    real        freq_hz_approx;

    assign amp_word = 9'd256;       // 50% 幅度

    // ── helper: f_word → approximate Hz for display ──────────
    function real fword_to_hz;
        input [31:0] fw;
        reg   [63:0] tmp;
        begin
            tmp = {32'd0, fw};
            fword_to_hz = (tmp * CLK_FREQ_HZ) / (64'd1 << 32);
        end
    endfunction

    // ══════════════════════════════════════════════════════════
    //  Clock
    // ══════════════════════════════════════════════════════════
    initial begin
        clk = 1'b0;
        forever #(CLK_HALF_NS) clk = ~clk;
    end

    // ══════════════════════════════════════════════════════════
    //  VCD dump
    // ══════════════════════════════════════════════════════════
    initial begin
        $dumpfile("dds_sweep_tb.vcd");
        $dumpvars(0, dds_sweep_tb);
    end

    // ══════════════════════════════════════════════════════════
    //  DUT
    // ══════════════════════════════════════════════════════════
    dds_sweep_ctrl #(
        .CLK_FREQ_HZ           (CLK_FREQ_HZ),
        .START_FREQ_HZ         (START_FREQ_HZ),
        .STOP_FREQ_HZ          (STOP_FREQ_HZ),
        .STEP_FREQ_HZ          (STEP_FREQ_HZ),
        .STEP_PERIOD_CLKS      (STEP_PERIOD_CLKS),
        .REPEAT_SWEEP          (0),
        .RESET_PHASE_EACH_STEP (1)
    ) uut_ctrl (
        .clk        (clk),
        .rst_n      (rst_n),
        .sweep_en   (1'b1),
        .restart    (1'b0),
        .f_word     (f_word),
        .phase_clr  (phase_clr),
        .step_sync  (step_sync),
        .sweep_busy (sweep_busy),
        .sweep_done (sweep_done)
    );

    dds_top uut_dds (
        .clk       (clk),
        .rst_n     (rst_n),
        .phase_clr (phase_clr),
        .f_word    (f_word),
        .a_word    (amp_word),
        .wave_out  (wave_out)
    );

    // ══════════════════════════════════════════════════════════
    //  Test sequence
    // ══════════════════════════════════════════════════════════
    initial begin
        rst_n       = 1'b0;
        cycle_count = 0;
        step_count  = 0;
        freq_step   = 0;

        csv_fd = $fopen("dds_sweep_wave.csv", "w");
        $fdisplay(csv_fd, "time_ns,cycle,freq_step,f_word_hex,freq_hz,wave_out,step_sync");

        $display("\n");
        $display("╔════════════════════════════════════════════════════════╗");
        $display("║       DDS  Sweep  Testbench (Thesis Edition)          ║");
        $display("╠════════════════════════════════════════════════════════╣");
        $display("║  Clock        : %0d MHz                               ║", CLK_FREQ_HZ / 1_000_000);
        $display("║  Sweep range  : %0d → %0d Hz                          ║", START_FREQ_HZ, STOP_FREQ_HZ);
        $display("║  Step size    : %0d Hz                                ║", STEP_FREQ_HZ);
        $display("║  Dwell        : %0d clocks (%.1f us per step)         ║",
                 STEP_PERIOD_CLKS, STEP_PERIOD_CLKS * CLK_HALF_NS * 2.0 / 1000.0);
        $display("║  Phase reset  : each step                             ║");
        $display("╚════════════════════════════════════════════════════════╝");
        $display("\n");

        // ── reset ────────────────────────────────────────────
        repeat (5) @(posedge clk);
        rst_n = 1'b1;
        $display("[%8t ns] > Reset released", $time);

        // ── wait for sweep_done (with timeout) ───────────────
        fork
            begin
                wait (sweep_done);
                $display("[%8t ns] > sweep_done asserted", $time);
            end
            begin
                repeat (MAX_SIM_CYCLES) @(posedge clk);
                $display("[%8t ns] *** TIMEOUT — sweep_done did not assert within %0d cycles",
                         $time, MAX_SIM_CYCLES);
                $fclose(csv_fd);
                $finish;
            end
        join_any
        disable fork;

        // ── observe a few extra cycles after sweep finishes ──
        repeat (100) @(posedge clk);

        // ── summary ──────────────────────────────────────────
        $display("\n");
        $display("╔════════════════════════════════════════════════════════╗");
        $display("║  Simulation finished                                  ║");
        $display("╠════════════════════════════════════════════════════════╣");
        $display("║  Total cycles   : %-5d                                ║", cycle_count);
        $display("║  Total steps    : %-5d                                ║", step_count);
        $display("║  Sim time       : %-8t ns                             ║", $time);
        $display("║  CSV saved to   : dds_sweep_wave.csv                  ║");
        $display("║  VCD saved to   : dds_sweep_tb.vcd                    ║");
        $display("║  Plot script    : python plot_dds_sweep.py             ║");
        $display("╚════════════════════════════════════════════════════════╝");
        $display("\n");

        $fclose(csv_fd);
        $finish;
    end

    // ══════════════════════════════════════════════════════════
    //  freq_step tracking — increments at each step_sync
    // ══════════════════════════════════════════════════════════
    always @(posedge clk or negedge rst_n) begin
        if (!rst_n)
            freq_step <= 8'd0;
        else if (step_sync)
            freq_step <= freq_step + 8'd1;
    end

    // ══════════════════════════════════════════════════════════
    //  Cycle counter, CSV logger, console reporter
    // ══════════════════════════════════════════════════════════
    always @(posedge clk) begin
        if (rst_n) begin
            cycle_count <= cycle_count + 1;
            freq_hz_approx = fword_to_hz(f_word);

            // ── CSV: one row per cycle ───────────────────────
            $fdisplay(csv_fd, "%0d,%0d,%0d,0x%08h,%0.0f,%0d,%b",
                      $time, cycle_count, freq_step, f_word,
                      freq_hz_approx, wave_out, step_sync);

            // ── console: step boundary ───────────────────────
            if (step_sync) begin
                step_count <= step_count + 1;
                $display("[%8t ns] ------------------------------", $time);
                $display("[%8t ns]  STEP %0d  f = %.1f MHz  f_word = 0x%08h",
                         $time, freq_step + 1, freq_hz_approx / 1e6, f_word);
            end
        end
    end

endmodule

src/sim/dds_sweep_tb.vcd
$date
	Tue May 05 17:22:31 2026
$end
$version
	ModelSim Version 10.5b
$end
$timescale
	1ps
$end

$scope module dds_sweep_tb $end
$var parameter 32 ! DDS_A_WORD_WIDTH $end
$var parameter 32 " CLK_HALF_NS $end
$var parameter 32 # MAX_SIM_CYCLES $end
$var parameter 32 $ CLK_FREQ_HZ $end
$var parameter 32 % START_FREQ_HZ $end
$var parameter 32 & STOP_FREQ_HZ $end
$var parameter 32 ' STEP_FREQ_HZ $end
$var parameter 32 ( STEP_PERIOD_CLKS $end
$var reg 1 ) clk $end
$var reg 1 * rst_n $end
$var wire 1 + f_word [31] $end
$var wire 1 , f_word [30] $end
$var wire 1 - f_word [29] $end
$var wire 1 . f_word [28] $end
$var wire 1 / f_word [27] $end
$var wire 1 0 f_word [26] $end
$var wire 1 1 f_word [25] $end
$var wire 1 2 f_word [24] $end
$var wire 1 3 f_word [23] $end
$var wire 1 4 f_word [22] $end
$var wire 1 5 f_word [21] $end
$var wire 1 6 f_word [20] $end
$var wire 1 7 f_word [19] $end
$var wire 1 8 f_word [18] $end
$var wire 1 9 f_word [17] $end
$var wire 1 : f_word [16] $end
$var wire 1 ; f_word [15] $end
$var wire 1 < f_word [14] $end
$var wire 1 = f_word [13] $end
$var wire 1 > f_word [12] $end
$var wire 1 ? f_word [11] $end
$var wire 1 @ f_word [10] $end
$var wire 1 A f_word [9] $end
$var wire 1 B f_word [8] $end
$var wire 1 C f_word [7] $end
$var wire 1 D f_word [6] $end
$var wire 1 E f_word [5] $end
$var wire 1 F f_word [4] $end
$var wire 1 G f_word [3] $end
$var wire 1 H f_word [2] $end
$var wire 1 I f_word [1] $end
$var wire 1 J f_word [0] $end
$var wire 1 K phase_clr $end
$var wire 1 L step_sync $end
$var wire 1 M sweep_busy $end
$var wire 1 N sweep_done $end
$var wire 1 O wave_out [7] $end
$var wire 1 P wave_out [6] $end
$var wire 1 Q wave_out [5] $end
$var wire 1 R wave_out [4] $end
$var wire 1 S wave_out [3] $end
$var wire 1 T wave_out [2] $end
$var wire 1 U wave_out [1] $end
$var wire 1 V wave_out [0] $end
$var wire 1 W amp_word [8] $end
$var wire 1 X amp_word [7] $end
$var wire 1 Y amp_word [6] $end
$var wire 1 Z amp_word [5] $end
$var wire 1 [ amp_word [4] $end
$var wire 1 \ amp_word [3] $end
$var wire 1 ] amp_word [2] $end
$var wire 1 ^ amp_word [1] $end
$var wire 1 _ amp_word [0] $end
$var reg 8 ` freq_step [7:0] $end
$var integer 32 a cycle_count $end
$var integer 32 b step_count $end
$var integer 32 c csv_fd $end
$var real 0 d freq_hz_approx $end

$scope function fword_to_hz $end
$var real 0 e fword_to_hz $end
$var reg 32 f fw [31:0] $end
$var reg 64 g tmp [63:0] $end
$upscope $end

$scope module uut_ctrl $end
$var parameter 32 h CLK_FREQ_HZ $end
$var parameter 32 i START_FREQ_HZ $end
$var parameter 32 j STOP_FREQ_HZ $end
$var parameter 32 k STEP_FREQ_HZ $end
$var parameter 32 l STEP_PERIOD_CLKS $end
$var parameter 32 m REPEAT_SWEEP $end
$var parameter 32 n RESET_PHASE_EACH_STEP $end
$var parameter 32 o START_WORD $end
$var parameter 32 p STOP_WORD $end
$var parameter 32 q STEP_WORD $end
$var parameter 1 r SWEEP_UP $end
$var parameter 32 s SAFE_STEP_PERIOD_CLKS $end
$var wire 1 t clk $end
$var wire 1 u rst_n $end
$var wire 1 v sweep_en $end
$var wire 1 w restart $end
$var reg 32 x f_word [31:0] $end
$var reg 1 y phase_clr $end
$var reg 1 z step_sync $end
$var reg 1 { sweep_busy $end
$var reg 1 | sweep_done $end
$var reg 32 } dwell_cnt [31:0] $end

$scope function hz_to_fword $end
$var reg 32 ~ hz_to_fword [31:0] $end
$var integer 32 !! freq_hz $end
$var reg 64 "! numerator [63:0] $end
$upscope $end
$upscope $end

$scope module uut_dds $end
$var wire 1 #! clk $end
$var wire 1 $! rst_n $end
$var wire 1 K phase_clr $end
$var wire 1 + f_word [31] $end
$var wire 1 , f_word [30] $end
$var wire 1 - f_word [29] $end
$var wire 1 . f_word [28] $end
$var wire 1 / f_word [27] $end
$var wire 1 0 f_word [26] $end
$var wire 1 1 f_word [25] $end
$var wire 1 2 f_word [24] $end
$var wire 1 3 f_word [23] $end
$var wire 1 4 f_word [22] $end
$var wire 1 5 f_word [21] $end
$var wire 1 6 f_word [20] $end
$var wire 1 7 f_word [19] $end
$var wire 1 8 f_word [18] $end
$var wire 1 9 f_word [17] $end
$var wire 1 : f_word [16] $end
$var wire 1 ; f_word [15] $end
$var wire 1 < f_word [14] $end
$var wire 1 = f_word [13] $end
$var wire 1 > f_word [12] $end
$var wire 1 ? f_word [11] $end
$var wire 1 @ f_word [10] $end
$var wire 1 A f_word [9] $end
$var wire 1 B f_word [8] $end
$var wire 1 C f_word [7] $end
$var wire 1 D f_word [6] $end
$var wire 1 E f_word [5] $end
$var wire 1 F f_word [4] $end
$var wire 1 G f_word [3] $end
$var wire 1 H f_word [2] $end
$var wire 1 I f_word [1] $end
$var wire 1 J f_word [0] $end
$var wire 1 W a_word [8] $end
$var wire 1 X a_word [7] $end
$var wire 1 Y a_word [6] $end
$var wire 1 Z a_word [5] $end
$var wire 1 [ a_word [4] $end
$var wire 1 \ a_word [3] $end
$var wire 1 ] a_word [2] $end
$var wire 1 ^ a_word [1] $end
$var wire 1 _ a_word [0] $end
$var wire 1 O wave_out [7] $end
$var wire 1 P wave_out [6] $end
$var wire 1 Q wave_out [5] $end
$var wire 1 R wave_out [4] $end
$var wire 1 S wave_out [3] $end
$var wire 1 T wave_out [2] $end
$var wire 1 U wave_out [1] $end
$var wire 1 V wave_out [0] $end
$var wire 1 %! rom_addr [9] $end
$var wire 1 &! rom_addr [8] $end
$var wire 1 '! rom_addr [7] $end
$var wire 1 (! rom_addr [6] $end
$var wire 1 )! rom_addr [5] $end
$var wire 1 *! rom_addr [4] $end
$var wire 1 +! rom_addr [3] $end
$var wire 1 ,! rom_addr [2] $end
$var wire 1 -! rom_addr [1] $end
$var wire 1 .! rom_addr [0] $end
$var wire 1 /! sin_q_raw [9] $end
$var wire 1 0! sin_q_raw [8] $end
$var wire 1 1! sin_q_raw [7] $end
$var wire 1 2! sin_q_raw [6] $end
$var wire 1 3! sin_q_raw [5] $end
$var wire 1 4! sin_q_raw [4] $end
$var wire 1 5! sin_q_raw [3] $end
$var wire 1 6! sin_q_raw [2] $end
$var wire 1 7! sin_q_raw [1] $end
$var wire 1 8! sin_q_raw [0] $end
$var wire 1 9! wave_raw [7] $end
$var wire 1 :! wave_raw [6] $end
$var wire 1 ;! wave_raw [5] $end
$var wire 1 <! wave_raw [4] $end
$var wire 1 =! wave_raw [3] $end
$var wire 1 >! wave_raw [2] $end
$var wire 1 ?! wave_raw [1] $end
$var wire 1 @! wave_raw [0] $end

$scope module u_dds_phase $end
$var wire 1 #! clk $end
$var wire 1 $! rst_n $end
$var wire 1 K phase_clr $end
$var wire 1 + f_word [31] $end
$var wire 1 , f_word [30] $end
$var wire 1 - f_word [29] $end
$var wire 1 . f_word [28] $end
$var wire 1 / f_word [27] $end
$var wire 1 0 f_word [26] $end
$var wire 1 1 f_word [25] $end
$var wire 1 2 f_word [24] $end
$var wire 1 3 f_word [23] $end
$var wire 1 4 f_word [22] $end
$var wire 1 5 f_word [21] $end
$var wire 1 6 f_word [20] $end
$var wire 1 7 f_word [19] $end
$var wire 1 8 f_word [18] $end
$var wire 1 9 f_word [17] $end
$var wire 1 : f_word [16] $end
$var wire 1 ; f_word [15] $end
$var wire 1 < f_word [14] $end
$var wire 1 = f_word [13] $end
$var wire 1 > f_word [12] $end
$var wire 1 ? f_word [11] $end
$var wire 1 @ f_word [10] $end
$var wire 1 A f_word [9] $end
$var wire 1 B f_word [8] $end
$var wire 1 C f_word [7] $end
$var wire 1 D f_word [6] $end
$var wire 1 E f_word [5] $end
$var wire 1 F f_word [4] $end
$var wire 1 G f_word [3] $end
$var wire 1 H f_word [2] $end
$var wire 1 I f_word [1] $end
$var wire 1 J f_word [0] $end
$var wire 1 %! rom_addr [9] $end
$var wire 1 &! rom_addr [8] $end
$var wire 1 '! rom_addr [7] $end
$var wire 1 (! rom_addr [6] $end
$var wire 1 )! rom_addr [5] $end
$var wire 1 *! rom_addr [4] $end
$var wire 1 +! rom_addr [3] $end
$var wire 1 ,! rom_addr [2] $end
$var wire 1 -! rom_addr [1] $end
$var wire 1 .! rom_addr [0] $end
$var reg 32 A! phase_acc [31:0] $end
$upscope $end

$scope module u_sin $end
$var wire 1 %! address [9] $end
$var wire 1 &! address [8] $end
$var wire 1 '! address [7] $end
$var wire 1 (! address [6] $end
$var wire 1 )! address [5] $end
$var wire 1 *! address [4] $end
$var wire 1 +! address [3] $end
$var wire 1 ,! address [2] $end
$var wire 1 -! address [1] $end
$var wire 1 .! address [0] $end
$var wire 1 #! clock $end
$var reg 10 B! q [9:0] $end
$var integer 32 C! i $end
$var real 0 D! phase $end
$var real 0 E! val $end
$upscope $end

$scope module u_dds_amp $end
$var wire 1 #! clk $end
$var wire 1 $! rst_n $end
$var wire 1 9! wave_in [7] $end
$var wire 1 :! wave_in [6] $end
$var wire 1 ;! wave_in [5] $end
$var wire 1 <! wave_in [4] $end
$var wire 1 =! wave_in [3] $end
$var wire 1 >! wave_in [2] $end
$var wire 1 ?! wave_in [1] $end
$var wire 1 @! wave_in [0] $end
$var wire 1 W a_word [8] $end
$var wire 1 X a_word [7] $end
$var wire 1 Y a_word [6] $end
$var wire 1 Z a_word [5] $end
$var wire 1 [ a_word [4] $end
$var wire 1 \ a_word [3] $end
$var wire 1 ] a_word [2] $end
$var wire 1 ^ a_word [1] $end
$var wire 1 _ a_word [0] $end
$var reg 8 F! wave_out [7:0] $end
$var wire 1 G! wave_signed [8] $end
$var wire 1 H! wave_signed [7] $end
$var wire 1 I! wave_signed [6] $end
$var wire 1 J! wave_signed [5] $end
$var wire 1 K! wave_signed [4] $end
$var wire 1 L! wave_signed [3] $end
$var wire 1 M! wave_signed [2] $end
$var wire 1 N! wave_signed [1] $end
$var wire 1 O! wave_signed [0] $end
$var wire 1 P! mult_result [18] $end
$var wire 1 Q! mult_result [17] $end
$var wire 1 R! mult_result [16] $end
$var wire 1 S! mult_result [15] $end
$var wire 1 T! mult_result [14] $end
$var wire 1 U! mult_result [13] $end
$var wire 1 V! mult_result [12] $end
$var wire 1 W! mult_result [11] $end
$var wire 1 X! mult_result [10] $end
$var wire 1 Y! mult_result [9] $end
$var wire 1 Z! mult_result [8] $end
$var wire 1 [! mult_result [7] $end
$var wire 1 \! mult_result [6] $end
$var wire 1 ]! mult_result [5] $end
$var wire 1 ^! mult_result [4] $end
$var wire 1 _! mult_result [3] $end
$var wire 1 `! mult_result [2] $end
$var wire 1 a! mult_result [1] $end
$var wire 1 b! mult_result [0] $end
$var wire 1 c! scaled_wave [9] $end
$var wire 1 d! scaled_wave [8] $end
$var wire 1 e! scaled_wave [7] $end
$var wire 1 f! scaled_wave [6] $end
$var wire 1 g! scaled_wave [5] $end
$var wire 1 h! scaled_wave [4] $end
$var wire 1 i! scaled_wave [3] $end
$var wire 1 j! scaled_wave [2] $end
$var wire 1 k! scaled_wave [1] $end
$var wire 1 l! scaled_wave [0] $end
$upscope $end
$upscope $end
$upscope $end
$enddefinitions $end
#0
$dumpvars
b101000111101011100001010001 ~
b1111010000100100000000000000000000000000000000000000 "!
0)
0*
b0 `
bx f
bx g
b101000111101011100001010001 x
0y
0z
0{
0|
b0 }
b0 A!
bx B!
b10000000 F!
b1001 !
b1010 "
b100111000100000 #
b10111110101111000010000000 $
b11110100001001000000 %
b1111010000100100000000 &
b11110100001001000000 '
b111110100 (
b10111110101111000010000000 h
b11110100001001000000 i
b1111010000100100000000 j
b11110100001001000000 k
b111110100 l
b0 m
b1 n
b101000111101011100001010001 o
b10100011110101110000101000111 p
b101000111101011100001010001 q
b1 r
b111110100 s
b11110100001001000000 !!
b0 a
b0 b
b10000000000000000000000000000011 c
b10000000000 C!
r0 d
r0 e
r6.277049384028044 D!
r508.8645629442821 E!
1J
0I
0H
0G
1F
0E
1D
0C
0B
0A
0@
1?
1>
1=
0<
1;
0:
19
18
17
16
05
04
03
12
01
10
0/
0.
0-
0,
0+
0K
0L
0M
0N
0V
0U
0T
0S
0R
0Q
0P
1O
0_
0^
0]
0\
0[
0Z
0Y
0X
1W
0.!
0-!
0,!
0+!
0*!
0)!
0(!
0'!
0&!
0%!
x8!
x7!
x6!
x5!
x4!
x3!
x2!
x1!
x0!
x/!
x@!
x?!
x>!
x=!
x<!
x;!
x:!
x9!
xO!
xN!
xM!
xL!
xK!
xJ!
xI!
xH!
xG!
xb!
xa!
x`!
x_!
x^!
x]!
x\!
x[!
xZ!
xY!
xX!
xW!
xV!
xU!
xT!
xS!
xR!
xQ!
xP!
xl!
xk!
xj!
xi!
xh!
xg!
xf!
xe!
xd!
xc!
0w
1v
0t
0u
0#!
0$!
$end
#10000
1)
1#!
1t
b1000000000 B!
08!
07!
06!
05!
04!
03!
02!
01!
00!
1/!
0@!
0?!
0>!
0=!
0<!
0;!
0:!
19!
0O!
0N!
0M!
0L!
0K!
0J!
0I!
0H!
0G!
0b!
0a!
0`!
0_!
0^!
0]!
0\!
0[!
0Z!
0Y!
0X!
0W!
0V!
0U!
0T!
0S!
0R!
0Q!
0P!
0l!
0k!
0j!
0i!
0h!
0g!
0f!
1e!
0d!
0c!
#20000
0)
0#!
0t
#30000
1)
1#!
1t
#40000
0)
0#!
0t
#50000
1)
1#!
1t
#60000
0)
0#!
0t
#70000
1)
1#!
1t
#80000
0)
0#!
0t
#90000
1)
1#!
1t
1*
1$!
1u
#100000
0)
0#!
0t
#110000
1)
1#!
1t
b101000111101011100001010001 f
b101000111101011100001010001 g
r999999 e
r999999 d
1{
b1 }
b101000111101011100001010001 A!
b1 a
1M
1,!
1*!
#120000
0)
0#!
0t
#130000
1)
1#!
1t
b10 }
b1010001111010111000010100010 A!
b1000111110 B!
b10 a
17!
16!
15!
14!
13!
0,!
1+!
0*!
1)!
1@!
1?!
1>!
1=!
1O!
1N!
1M!
1L!
1Z!
1Y!
1X!
1W!
1l!
1k!
1j!
#140000
0)
0#!
0t
#150000
1)
1#!
1t
b11 }
b1111010111000010100011110011 A!
b1001111100 B!
b10000111 F!
b11 a
1V
1U
1T
07!
12!
1.!
1,!
1*!
1<!
1K!
1V!
1i!
#160000
0)
0#!
0t
#170000
1)
1#!
1t
b100 }
b10100011110101110000101000100 A!
b1010111010 B!
b10001111 F!
b100 a
1S
17!
06!
02!
11!
0,!
0+!
0)!
1(!
0@!
0<!
1;!
0O!
0K!
1J!
0Z!
0V!
1U!
0i!
1h!
#180000
0)
0#!
0t
#190000
1)
1#!
1t
b101 }
b11001100110011001100110010101 A!
b1011110011 B!
b10010111 F!
b101 a
0S
1R
18!
05!
12!
0.!
1-!
1,!
0*!
1)!
0?!
1<!
0N!
1K!
0Y!
1V!
0l!
1i!
#200000
0)
0#!
0t
#210000
1)
1#!
1t
b110 }
b11110101110000101000111100110 A!
b1100101011 B!
b10011110 F!
b110 a
0V
1S
15!
04!
02!
01!
10!
0,!
1+!
1*!
1?!
0>!
0<!
0;!
1:!
1N!
0M!
0K!
0J!
1I!
1Y!
0X!
0V!
0U!
1T!
1l!
0k!
0i!
0h!
1g!
#220000
0)
0#!
0t
#230000
1)
1#!
1t
b111 }
b100011110101110000101000110111 A!
b1101011011 B!
b10100101 F!
b111 a
1V
0U
0S
0R
1Q
14!
03!
12!
1.!
1,!
0*!
0)!
0(!
1'!
1>!
0=!
1<!
1M!
0L!
1K!
1X!
0W!
1V!
1k!
0j!
1i!
#240000
0)
0#!
0t
#250000
1)
1#!
1t
b1000 }
b101000111101011100001010001000 A!
b1110001001 B!
b10101011 F!
b1000 a
1U
0T
1S
07!
04!
02!
11!
0,!
0+!
1)!
0>!
0<!
1;!
0M!
0K!
1J!
0X!
0V!
1U!
0k!
0i!
1h!
#260000
0)
0#!
0t
#270000
1)
1#!
1t
b1001 }
b101110000101000111101011011001 A!
b1110101110 B!
b10110001 F!
b1001 a
0U
0S
1R
08!
17!
16!
13!
0.!
0-!
1+!
1*!
1@!
1=!
1O!
1L!
1Z!
1W!
1j!
#280000
0)
0#!
0t
#290000
1)
1#!
1t
b1010 }
b110011001100110011001100101010 A!
b1111001101 B!
b10110101 F!
b1010 a
1T
18!
07!
03!
12!
1,!
0*!
0)!
1(!
0=!
1<!
0L!
1K!
0W!
1V!
0j!
1i!
#300000
0)
0#!
0t
#310000
1)
1#!
1t
b1011 }
b111000010100011110101101111011 A!
b1111100101 B!
b10111001 F!
b1011 a
0T
1S
05!
13!
1.!
0,!
0+!
1)!
0?!
1=!
0N!
1L!
0Y!
1W!
0l!
1j!
#320000
0)
0#!
0t
#330000
1)
1#!
1t
b1100 }
b111101011100001010001111001100 A!
b1111110101 B!
b10111100 F!
b1100 a
0V
1T
14!
1,!
1*!
1>!
1M!
1X!
1k!
#340000
0)
0#!
0t
#350000
1)
1#!
1t
b1101 }
b1000010100011110101110000011101 A!
b1111111101 B!
b10111110 F!
b1101 a
1U
15!
0.!
1-!
0,!
1+!
0*!
0)!
0(!
0'!
1&!
1?!
1N!
1Y!
1l!
#360000
0)
0#!
0t
